reversi_board/__init__.py
reversi_board/board.py
reversi_board/consts.py
reversi_board/game.py
reversi_board/player.py
reversi_board-0.1.1.dist-info/METADATA
reversi_board-0.1.1.dist-info/RECORD
reversi_board-0.1.1.dist-info/WHEEL
reversi_board-0.1.1.dist-info/top_level.txt
