Metadata-Version: 2.1
Name: reversi-board
Version: 0.1.1
Summary: reversi board
Home-page: https://github.com/naari3/reversi_board-py
Author: naari3
Author-email: naari.named@gmail.com
License: MIT
Keywords: reversi othero
Platform: UNKNOWN
Classifier: Programming Language :: Python :: 3.6
Requires-Dist: numpy (>=1.15.3)
